odoo10_addon_account_bank_statement_line_reconciliation-10.0.1.0.0.99.dev4-py2.7-nspkg.pth
odoo/addons/account_bank_statement_line_reconciliation/README.rst
odoo/addons/account_bank_statement_line_reconciliation/__init__.py
odoo/addons/account_bank_statement_line_reconciliation/__manifest__.py
odoo/addons/account_bank_statement_line_reconciliation/i18n/account_bank_statement_line_reconciliation.pot
odoo/addons/account_bank_statement_line_reconciliation/models/__init__.py
odoo/addons/account_bank_statement_line_reconciliation/models/account_bank_statement.py
odoo/addons/account_bank_statement_line_reconciliation/models/company.py
odoo/addons/account_bank_statement_line_reconciliation/models/res_config_settings.py
odoo/addons/account_bank_statement_line_reconciliation/static/description/icon.png
odoo/addons/account_bank_statement_line_reconciliation/views/res_config_settings_views.xml
odoo/addons/account_bank_statement_line_reconciliation/wizard/__init__.py
odoo/addons/account_bank_statement_line_reconciliation/wizard/account_bank_statement_line_reconciliation_wizard.py
odoo/addons/account_bank_statement_line_reconciliation/wizard/account_bank_statement_line_reconciliation_wizard.xml
odoo10_addon_account_bank_statement_line_reconciliation-10.0.1.0.0.99.dev4.dist-info/METADATA
odoo10_addon_account_bank_statement_line_reconciliation-10.0.1.0.0.99.dev4.dist-info/RECORD
odoo10_addon_account_bank_statement_line_reconciliation-10.0.1.0.0.99.dev4.dist-info/WHEEL
odoo10_addon_account_bank_statement_line_reconciliation-10.0.1.0.0.99.dev4.dist-info/namespace_packages.txt
odoo10_addon_account_bank_statement_line_reconciliation-10.0.1.0.0.99.dev4.dist-info/top_level.txt
